nheatmap/__init__.py
nheatmap/plot.py
nheatmap/scripts.py
nheatmap-0.1.4.dist-info/LICENSE
nheatmap-0.1.4.dist-info/METADATA
nheatmap-0.1.4.dist-info/WHEEL
nheatmap-0.1.4.dist-info/top_level.txt
nheatmap-0.1.4.dist-info/RECORD
