Metadata-Version: 2.1
Name: nheatmap
Version: 0.1.4
Summary: A painless and customizable tool to generate heatmap with hiearchical clustering results and additional data bars.
Home-page: https://github.com/xuesoso/nheatmap
Author: YSX
Author-email: xuesoso@gmail.com
License: LICENSE
Keywords: heatmap,hiearchical clustering,neat heatmap
Platform: UNKNOWN
Requires-Dist: matplotlib (>=3.0.3)
Requires-Dist: scipy (>=1.3.1)
Requires-Dist: numpy (>=1.17.2)
Requires-Dist: pandas (>=0.25.1)
Requires-Dist: packaging
